pilot/__init__.py
pilot/client.py
pilot/config.py
pilot/context.py
pilot/exc.py
pilot/globus_clients.py
pilot/logging_cfg.py
pilot/profile.py
pilot/project.py
pilot/search.py
pilot/search_discovery.py
pilot/search_parse.py
pilot/transfer_log.py
pilot/validation.py
pilot/version.py
pilot/analysis/__init__.py
pilot/analysis/image.py
pilot/analysis/mimetypes.py
pilot/analysis/pandas.py
pilot/commands/__init__.py
pilot/commands/endpoint_utils.py
pilot/commands/input_validation.py
pilot/commands/main.py
pilot/commands/path_utils.py
pilot/commands/auth/__init__.py
pilot/commands/auth/auth_commands.py
pilot/commands/project/__init__.py
pilot/commands/project/index.py
pilot/commands/project/project.py
pilot/commands/search/__init__.py
pilot/commands/search/delete.py
pilot/commands/search/search_commands.py
pilot/commands/transfer/__init__.py
pilot/commands/transfer/analyze.py
pilot/commands/transfer/status_commands.py
pilot/commands/transfer/transfer_commands.py
pilot/schemas/__init__.py
pilot/schemas/dataset.json
pilot/schemas/dc.json
pilot/schemas/field_metadata.json
pilot/schemas/files.json
pilot/schemas/project_metadata.json
pilot/schemas/user_provided_metadata.json
tests/__init__.py
tests/unit/__init__.py
tests/unit/conftest.py
tests/unit/mocks.py
tests/unit/test_analyze.py
tests/unit/test_client_data_utils.py
tests/unit/test_client_path_resolution.py
tests/unit/test_client_upload.py
tests/unit/test_command_auth.py
tests/unit/test_command_delete.py
tests/unit/test_command_index.py
tests/unit/test_command_main.py
tests/unit/test_command_search.py
tests/unit/test_command_transfer.py
tests/unit/test_config.py
tests/unit/test_context.py
tests/unit/test_gather_metadata.py
tests/unit/test_mimetypes.py
tests/unit/test_profile.py
tests/unit/test_schemas.py
tests/unit/test_search.py
tests/unit/test_search_discovery.py
tests/unit/test_search_parse.py
tests/unit/test_transfer_log.py
globus_pilot-0.7.0.dist-info/METADATA
globus_pilot-0.7.0.dist-info/WHEEL
globus_pilot-0.7.0.dist-info/entry_points.txt
globus_pilot-0.7.0.dist-info/top_level.txt
globus_pilot-0.7.0.dist-info/RECORD
