Metadata-Version: 2.1
Name: globus-pilot
Version: 0.7.0
Summary: A CLI tool for cataloging pilot 1 data
Home-page: https://github.com/globusonline/pilot1-tools/tree/master
Maintainer: globus
Maintainer-email: support@globus.org
License: UNKNOWN
Platform: UNKNOWN
Classifier: Intended Audience :: Science/Research
Classifier: Intended Audience :: Developers
Classifier: Operating System :: POSIX
Classifier: Operating System :: MacOS :: MacOS X
Classifier: Programming Language :: Python
Classifier: Programming Language :: Python :: 3.7
Classifier: Programming Language :: Python :: 3.8
Classifier: Programming Language :: Python :: 3.9
Requires-Dist: pytz
Requires-Dist: fair-research-login (>=0.2.0)
Requires-Dist: globus-sdk (<4.0.0>=3.0.0)
Requires-Dist: click (>=7.0)
Requires-Dist: colorama (>=0.4.1)
Requires-Dist: jsonschema (>=3.2.0)
Requires-Dist: configobj
Requires-Dist: python-slugify
Requires-Dist: requests-toolbelt
Requires-Dist: puremagic
Requires-Dist: Pillow
